PiesArt/__init__.py
PiesArt/_generator.py
PiesArt/ArtifactBank/RCS.mat
PiesArt/ArtifactBank/__init__.py
PiesArt/ArtifactEraser/__init__.py
PiesArt/ArtifactEraser/dataset.py
PiesArt/ArtifactEraser/model.py
PiesArt/ArtifactEraser/trainer.py
PiesArt/ArtifactEraser/_configs/RCS_ArtifactEraser_100k.yaml
PiesArt/ArtifactEraser/_configs/__init__.py
PiesArt/ArtifactEraser/_models/RCS_ArtifactEraser_100k_epoch_00000_iteration_99500_step_99500_ArtifactEraser.pt
PiesArt/ArtifactEraser/_models/__init__.py
PiesDL/__init__.py
PiesDL/models_generic.py
PiesGen/__init__.py
PiesGen/DCGAN/__init__.py
PiesGen/DCGAN/dataset.py
PiesGen/DCGAN/model.py
PiesGen/DCGAN/trainer.py
PiesGen/DCGAN/_configs/__init__.py
PiesGen/DCGAN/_models/__init__.py
PiesHyp/CyberPSG.py
PiesHyp/NSRR.py
PiesHyp/__init__.py
PiesHyp/analysis.py
PiesHyp/correct.py
PiesHyp/io.py
PiesHyp/utils.py
PiesHyp/visualisation.py
PiesPro/__init__.py
PiesPro/_config.py
PiesPro/feature.py
PiesPro/files.py
PiesPro/signal.py
PiesPro/stats.py
PiesPro/types.py
PiesPro/vector.py
PiesSleep/FeatureExtractor.py
PiesSleep/SpectralFeatures.py
PiesSleep/__init__.py
PiesSleep/models.py
PiesSleep/modules/__init__.py
PiesSleep/modules/feature.py
PiesSleep/modules/stats.py
PiesWaveDet/WaveDetector.py
PiesWaveDet/__init__.py
_annotation_tools/XML_CVAT.py
_annotation_tools/XML_CyberPSG.py
_annotation_tools/__init__.py
_annotation_tools/xml_structured_parsing/__init__.py
_annotation_tools/xml_structured_parsing/myXML.py
piespro-0.0.3.data/data/PiesArt_artifact/RCS.mat
piespro-0.0.3.data/data/PiesArt_cfg/RCS_ArtifactEraser_100k.yaml
piespro-0.0.3.data/data/PiesArt_mdl/RCS_ArtifactEraser_100k_epoch_00000_iteration_99500_step_99500_ArtifactEraser.pt
piespro-0.0.3.dist-info/LICENSE
piespro-0.0.3.dist-info/METADATA
piespro-0.0.3.dist-info/WHEEL
piespro-0.0.3.dist-info/top_level.txt
piespro-0.0.3.dist-info/RECORD
